zk_logo_maker/ZhenyanGB.ttf
zk_logo_maker/__init__.py
zk_logo_maker/__main__.py
zk_logo_maker-1.0.5.dist-info/METADATA
zk_logo_maker-1.0.5.dist-info/WHEEL
zk_logo_maker-1.0.5.dist-info/entry_points.txt
zk_logo_maker-1.0.5.dist-info/top_level.txt
zk_logo_maker-1.0.5.dist-info/RECORD
