Metadata-Version: 2.1
Name: zk-logo-maker
Version: 1.0.5
Summary: Tool to make zhike logos
Home-page: https://github.com/caojianfeng/zk_logo_maker
Author: JeffreyCao
Author-email: jeffreycao1024@gmail.com
License: MIT Licence
Keywords: pip,zk_logo_maker
Platform: any
Classifier: Programming Language :: Python :: 3
Classifier: License :: OSI Approved :: MIT License
Classifier: Operating System :: OS Independent
Requires-Python: >=3.6
Requires-Dist: Pillow
